<?xml version="1.0" encoding="UTF-8"?>
<dbConfig>
	<!--VSS-->
	<vision.apollo.app.domain.AppType code="vss" name="视频督察系统" iconId="6" serverType="1" status="1" persist="1" remark="视频督察系统" createTime="2014-04-04 09:11:48" updateTime="2014-04-04 09:11:50" />
	<vision.apollo.ups.domain.AppSystem code="200010" name="视频督察系统" status="1" persist="1" url="vas" remark="视频督察系统" typeCode="vss" createTime="2014-09-28 09:12:21" />
	<vision.apollo.app.domain.AppService code="1010" appCode="200010" domainCode="100001" ip="127.0.0.1" serverPort="1291" httpPort="80" persist="1" protocol="rmi" />
	
	<!--权限-->
	<vision.apollo.ups.domain.AuthElement code="VSS_000000" appTypeCode="vss" name="视频督察系统" parentCode="00000" nodeTree=",00000,VSS_000000," dataAuth="0" type="0" status="1" persist="1" weight="0" remark="视频督察系统" createTime="2014-09-28 09:12:21" />
	<vision.apollo.ups.domain.AuthElement code="VSS_000001" appTypeCode="vss" name="视频督察系统-应用" parentCode="VSS_000000" nodeTree=",00000,VSS_000000,VSS_000001," dataAuth="0" type="0" status="1" persist="1" weight="99" remark="视频督察系统-应用" createTime="2014-09-28 09:12:21" />
	<vision.apollo.ups.domain.AuthElement code="vas_010000" appTypeCode="vss" name="视频督察" parentCode="VSS_000001" nodeTree=",00000,VSS_000000,VSS_000001,vas_010000," licKey="MdlVideoSupervision" dataAuth="0" type="0" status="1" persist="1" weight="99" remark="视频督察" createTime="2014-09-28 09:12:21" />
		<vision.apollo.ups.domain.AuthElement code="vas_010100" appTypeCode="vss" name="实时预览" parentCode="vas_010000" nodeTree=",00000,VSS_000000,VSS_000001,vas_010000,vas_010100," dataAuth="1" collectionCode="C10001" type="0" status="1" persist="1" weight="99" remark="实时预览" createTime="2013-09-16 16:33:57" />	
		<vision.apollo.ups.domain.AuthElement code="vas_010200" appTypeCode="vss" name="云台控制" parentCode="vas_010000" nodeTree=",00000,VSS_000000,VSS_000001,vas_010000,vas_010200," dataAuth="1" collectionCode="C10001" type="0" status="1" persist="1" weight="98" remark="云台控制" createTime="2013-09-16 16:33:57" />
		<vision.apollo.ups.domain.AuthElement code="vas_010300" appTypeCode="vss" name="云台配置" parentCode="vas_010000" nodeTree=",00000,VSS_000000,VSS_000001,vas_010000,vas_010300," dataAuth="1" collectionCode="C10001" type="0" status="1" persist="1" weight="97" remark="云台配置" createTime="2013-09-16 16:33:57" />
		<vision.apollo.ups.domain.AuthElement code="vas_010400" appTypeCode="vss" name="本地录像" parentCode="vas_010000" nodeTree=",00000,VSS_000000,VSS_000001,vas_010000,vas_010400," dataAuth="1" collectionCode="C10001" type="0" status="1" persist="1" weight="96" remark="本地录像" createTime="2013-09-16 16:33:57" />
		<vision.apollo.ups.domain.AuthElement code="vas_010500" appTypeCode="vss" name="设备对讲" parentCode="vas_010000" nodeTree=",00000,VSS_000000,VSS_000001,vas_010000,vas_010500," dataAuth="1" collectionCode="C10001" type="0" status="1" persist="1" weight="95" remark="设备对讲" createTime="2013-09-16 16:33:57" />
		<vision.apollo.ups.domain.AuthElement code="vas_010600" appTypeCode="vss" name="IO报警控制" parentCode="vas_010000" nodeTree=",00000,VSS_000000,VSS_000001,vas_010000,vas_010600," dataAuth="1" collectionCode="C10001" type="0" status="1" persist="1" weight="95" remark="IO报警控制" createTime="2013-09-16 16:33:57" />
		<vision.apollo.ups.domain.AuthElement code="VSS_000110" appTypeCode="vss" name="讯问室音频" parentCode="vas_010000" nodeTree=",00000,VSS_000000,VSS_000001,vas_010000,VSS_000110," dataAuth="0" collectionCode="" type="0" status="1" persist="1" weight="94" remark="讯问室音频" createTime="2014-09-28 09:12:21" />
	<vision.apollo.ups.domain.AuthElement code="vas_020000" appTypeCode="vss" name="录像回放" parentCode="VSS_000001" nodeTree=",00000,VSS_000000,VSS_000001,vas_020000," licKey="MdlPlayback" dataAuth="0" type="0" status="1" persist="1" weight="98" remark="录像回放" createTime="2014-09-28 09:12:21" />
		<vision.apollo.ups.domain.AuthElement code="vas_020100" appTypeCode="vss" name="录像检索" parentCode="vas_020000" nodeTree=",00000,VSS_000000,VSS_000001,vas_020000,vas_020100," dataAuth="1" collectionCode="C10001" type="0" status="1" persist="1" weight="99" remark="录像检索" createTime="2013-09-16 16:33:57" />
		<vision.apollo.ups.domain.AuthElement code="vas_020200" appTypeCode="vss" name="录像播放" parentCode="vas_020000" nodeTree=",00000,VSS_000000,VSS_000001,vas_020000,vas_020200," dataAuth="1" collectionCode="C10001" type="0" status="1" persist="1" weight="98" remark="录像播放" createTime="2013-09-16 16:33:57" />
		<vision.apollo.ups.domain.AuthElement code="vas_020400" appTypeCode="vss" name="录像备份" parentCode="vas_020000" nodeTree=",00000,VSS_000000,VSS_000001,vas_020000,vas_020400," dataAuth="1" collectionCode="C10001" type="0" status="1" persist="1" weight="96" remark="录像备份" createTime="2013-09-16 16:33:57" />
	<vision.apollo.ups.domain.AuthElement code="VSS_000101" appTypeCode="vss" name="督察问题" parentCode="VSS_000001" nodeTree=",00000,VSS_000000,VSS_000001,VSS_000101," licKey="MdlSupervisionProblem" dataAuth="0" type="0" status="1" persist="1" weight="97" remark="督察问题" createTime="2014-09-28 09:12:21" />
		<vision.apollo.ups.domain.AuthElement code="VSS_000112" appTypeCode="vss" name="问题处置" parentCode="VSS_000101" nodeTree=",00000,VSS_000000,VSS_000001,VSS_000101,VSS_000112" licKey="" dataAuth="1" type="0" status="1" persist="1" weight="99" remark="归档查看" createTime="2014-09-28 09:12:21" />
		<vision.apollo.ups.domain.AuthElement code="VSS_000111" appTypeCode="vss" name="归档查看" parentCode="VSS_000101" nodeTree=",00000,VSS_000000,VSS_000001,VSS_000101,VSS_000111" licKey="" dataAuth="1" type="0" status="1" persist="1" weight="98" remark="归档查看" createTime="2014-09-28 09:12:21" />
	
	<vision.apollo.ups.domain.AuthElement code="VSS_000102" appTypeCode="vss" name="统计分析" parentCode="VSS_000001" nodeTree=",00000,VSS_000000,VSS_000001,VSS_000102," licKey="MdlIntelligenceWarning" dataAuth="0" type="0" status="1" persist="1" weight="94" remark="统计分析" createTime="2014-09-28 09:12:21" />
	<vision.apollo.ups.domain.AuthElement code="VSS_000103" appTypeCode="vss" name="智能预警" parentCode="VSS_000001" nodeTree=",00000,VSS_000000,VSS_000001,VSS_000103," licKey="MdlAnalysisManager" dataAuth="0" type="0" status="1" persist="1" weight="96" remark="智能预警" createTime="2014-09-28 09:12:21" />
	<vision.apollo.ups.domain.AuthElement code="VSS_000104" appTypeCode="vss" name="日志管理" parentCode="VSS_000001" nodeTree=",00000,VSS_000000,VSS_000001,VSS_000104," licKey="MdlLogManager" dataAuth="0" type="0" status="1" persist="1" weight="93" remark="日志管理" createTime="2014-09-28 09:12:21" />
	<!--
	<vision.apollo.ups.domain.AuthElement code="VSS_000105" appTypeCode="vss" name="值班管理" parentCode="VSS_000001" nodeTree=",00000,VSS_000000,VSS_000001,VSS_000105," licKey="MdlDutyManager" dataAuth="0" type="0" status="1" persist="1" weight="0" remark="值班管理" createTime="2014-09-28 09:12:21" />
	-->
	<vision.apollo.ups.domain.AuthElement code="VSS_000108" appTypeCode="vss" name="全文检索" parentCode="VSS_000001" nodeTree=",00000,VSS_000000,VSS_000001,VSS_000108," licKey="MdlGlobalSearch" dataAuth="0" type="0" status="1" persist="1" weight="95" remark="全文检索" createTime="2014-09-28 09:12:21" />
	<vision.apollo.ups.domain.AuthElement code="VSS_000109" appTypeCode="vss" name="公告管理" parentCode="VSS_000001" nodeTree=",00000,VSS_000000,VSS_000001,VSS_000109," dataAuth="0" type="0" status="1" persist="1" weight="0" remark="公告管理" createTime="2014-09-28 09:12:21" />
	
	<vision.apollo.ups.domain.AuthElement code="vas_150000" appTypeCode="vss" name="电视墙管理" parentCode="VSS_000001" nodeTree=",00000,VSS_000000,VSS_000001,vas_150000," dataAuth="0" type="0" status="1" persist="1" weight="85" remark="电视墙管理" createTime="2013-09-16 16:33:57"></vision.apollo.ups.domain.AuthElement>
		<vision.apollo.ups.domain.AuthElement code="vas_150100" appTypeCode="vss" name="电视墙控制" parentCode="vas_150000" nodeTree=",00000,VSS_000000,VSS_000001,vas_150000,vas_150100," dataAuth="1" collectionCode="C10001" type="0" status="1" persist="1" weight="97" remark="电视墙控制" createTime="2013-09-16 16:33:57"></vision.apollo.ups.domain.AuthElement>
		<vision.apollo.ups.domain.AuthElement code="vas_150200" appTypeCode="vss" name="电视墙配置及控制" parentCode="vas_150000" nodeTree=",00000,VSS_000000,VSS_000001,vas_150000,vas_150200," dataAuth="1" collectionCode="C10001" type="0" status="1" persist="1" weight="98" remark="电视墙配置及控制" createTime="2013-09-16 16:33:57"></vision.apollo.ups.domain.AuthElement>	
	
	<vision.apollo.ups.domain.AuthElement code="VSS_000002" appTypeCode="vss" name="视频督察系统-配置" parentCode="VSS_000000" nodeTree=",00000,VSS_000000,VSS_000002," dataAuth="0" type="0" status="1" persist="1" weight="98" remark="视频督察系统-配置" createTime="2014-09-28 09:12:21" />
	<vision.apollo.ups.domain.AuthElement code="VSS_000205" appTypeCode="vss" name="业务报警" parentCode="VSS_000002" nodeTree=",00000,VSS_000000,VSS_000002,VSS_000205," licKey="MdlSmartConfig" dataAuth="0" type="0" status="1" persist="1" weight="0" remark="智能配置" createTime="2014-09-28 09:12:21" />

	<vision.apollo.ups.domain.AuthElement code="VSS_000003" appTypeCode="vss" name="视频督察系统-督察权限" parentCode="VSS_000000" nodeTree=",00000,VSS_000000,VSS_000003," dataAuth="0" type="1" status="1" persist="1" weight="97" remark="视频督察系统-督察权限" createTime="2014-09-28 09:12:21" />
	<vision.apollo.ups.domain.AuthElement code="VSS_000300" appTypeCode="vss" name="督察员" parentCode="VSS_000003" nodeTree=",00000,VSS_000000,VSS_000003,VSS_000300," dataAuth="0" type="1" status="1" persist="1" weight="99" remark="督察员" createTime="2014-09-28 09:12:21" />
	<vision.apollo.ups.domain.AuthElement code="VSS_000301" appTypeCode="vss" name="业务领导" parentCode="VSS_000003" nodeTree=",00000,VSS_000000,VSS_000003,VSS_000301," dataAuth="0" type="1" status="1" persist="1" weight="98" remark="业务领导" createTime="2014-09-28 09:12:21" />
	<vision.apollo.ups.domain.AuthElement code="VSS_000302" appTypeCode="vss" name="督察领导" parentCode="VSS_000003" nodeTree=",00000,VSS_000000,VSS_000003,VSS_000302," dataAuth="0" type="1" status="1" persist="1" weight="97" remark="督察领导" createTime="2014-09-28 09:12:21" />

	<!-- VAS权限资源类型定义 -->
	<vision.apollo.ups.domain.AuthDataMap authCode="vas_010100" dataCode="CAMERA_INFO"></vision.apollo.ups.domain.AuthDataMap>
	<vision.apollo.ups.domain.AuthDataMap authCode="vas_010200" dataCode="CAMERA_INFO"></vision.apollo.ups.domain.AuthDataMap>
    <vision.apollo.ups.domain.AuthDataMap authCode="vas_010300" dataCode="CAMERA_INFO"></vision.apollo.ups.domain.AuthDataMap>
	<vision.apollo.ups.domain.AuthDataMap authCode="vas_010400" dataCode="CAMERA_INFO"></vision.apollo.ups.domain.AuthDataMap>
	<vision.apollo.ups.domain.AuthDataMap authCode="vas_010500" dataCode="DEVICE_INFO"></vision.apollo.ups.domain.AuthDataMap>
    <vision.apollo.ups.domain.AuthDataMap authCode="vas_010600" dataCode="IO_INFO"></vision.apollo.ups.domain.AuthDataMap>
	<vision.apollo.ups.domain.AuthDataMap authCode="vas_020100" dataCode="CAMERA_INFO"></vision.apollo.ups.domain.AuthDataMap>
	<vision.apollo.ups.domain.AuthDataMap authCode="vas_020200" dataCode="CAMERA_INFO"></vision.apollo.ups.domain.AuthDataMap>
	<vision.apollo.ups.domain.AuthDataMap authCode="vas_020400" dataCode="CAMERA_INFO"></vision.apollo.ups.domain.AuthDataMap>
	<vision.apollo.ups.domain.AuthDataMap authCode="vas_150100" dataCode="TVWALL_INFO"></vision.apollo.ups.domain.AuthDataMap>
	<vision.apollo.ups.domain.AuthDataMap authCode="vas_150200" dataCode="TVWALL_INFO"></vision.apollo.ups.domain.AuthDataMap>
	<vision.apollo.ups.domain.AuthDataMap authCode="vas_050100" dataCode="IO_INFO"></vision.apollo.ups.domain.AuthDataMap>
	
	
	<!-- 视频督察菜单 -->
	<vision.apollo.ups.domain.MenuTemplate code="vss_01" name="视频督察系统-应用" iconUrl="" authCode="VSS_000001" nodeTree=",0,vss_01," url="11" display="1" weight="99" appTypeCode="vss" parentCode="0" />
	<vision.apollo.ups.domain.MenuTemplate code="vss_0101" name="视频督察 " iconUrl="video-preview" authCode="vas_010000" nodeTree=",0,vss_01,vss_0101," url="/video/video!gotoVideo.action" openType="2" display="1" weight="99" appTypeCode="vss" parentCode="vss_01" />
	<vision.apollo.ups.domain.MenuTemplate code="vss_0107" name="录像回放" iconUrl="video-playback" authCode="vas_020000" nodeTree=",0,vss_01,vss_0107," url="/video/video!gotoPlaybackPage.action" openType="2" display="1" weight="98" appTypeCode="vss" parentCode="vss_01" />
	<vision.apollo.ups.domain.MenuTemplate code="vss_0102" name="督察问题" iconUrl="video-problem" authCode="VSS_000101" nodeTree=",0,vss_01,vss_0102," url="/web/supervise!goToCatalog.action" openType="2" display="1" weight="97" appTypeCode="vss" parentCode="vss_01" />
	<vision.apollo.ups.domain.MenuTemplate code="vss_0103" name="智能预警" iconUrl="alarm-config" authCode="VSS_000103" nodeTree=",0,vss_01,vss_0103," url="/alarm/alarm!getAlarmIndex.action" openType="2" display="1" weight="96" appTypeCode="vss" parentCode="vss_01" />
	<vision.apollo.ups.domain.MenuTemplate code="vss_0108" name="全文检索" iconUrl="search" authCode="VSS_000108" nodeTree=",0,vss_01,vss_0108," url="/search/search!gotoSearch.action" openType="2" display="1" weight="95" appTypeCode="vss" parentCode="vss_01" />
	<!--
	<vision.apollo.ups.domain.MenuTemplate code="vss_0106" name="值班管理" iconUrl="duty" authCode="VSS_000105" nodeTree=",0,vss_01,vss_0106," url="/duty/duty!gotoDuty.action" openType="2" display="1" weight="94" appTypeCode="vss" parentCode="vss_01" />
	-->
	<vision.apollo.ups.domain.MenuTemplate code="vss_0104" name="统计分析" iconUrl="operate" authCode="VSS_000102" nodeTree=",0,vss_01,vss_0104," url="/count/count!gotoCount.action" openType="2" display="1" weight="93" appTypeCode="vss" parentCode="vss_01" />
	<vision.apollo.ups.domain.MenuTemplate code="vss_0105" name="日志管理" iconUrl="log-m" authCode="VSS_000104" nodeTree=",0,vss_01,vss_0105," url="/operateLog!gotoOperateLog.action" openType="2" display="1" weight="92" appTypeCode="vss" parentCode="vss_01" />
	
	<vision.apollo.ups.domain.MenuTemplate code="vss_03" name="视频督察系统-配置" iconUrl="" authCode="VSS_000002" nodeTree=",0,vss_03," url="11" display="1" weight="99" appTypeCode="vss" parentCode="0" />
	<vision.apollo.ups.domain.MenuTemplate code="vss_0301" name="组织资源" iconUrl="organization-m" authCode="vms_010000" nodeTree=",0,vss_03,vss_0301," url="{'appCode':'100005','menuCode':'vms_01'}" openType="2" display="1" weight="99" appTypeCode="vss" parentCode="vss_03" />
	<vision.apollo.ups.domain.MenuTemplate code="vss_0302" name="用户管理" iconUrl="user-m" authCode="IMP_70003" nodeTree=",0,vss_03,vss_0302," url="{'appCode':'100001','menuCode':'0102'}" display="1" openType="1" weight="98" appTypeCode="vss" parentCode="vss_03" />
	<vision.apollo.ups.domain.MenuTemplate code="vss_0303" name="设备报警" iconUrl="alarm2-config" authCode="vms_020000" nodeTree=",0,vss_03,vss_0303," url="{'appCode':'100005','menuCode':'vms_02'}" openType="2" display="1" weight="97" appTypeCode="vss" parentCode="vss_03" />
	<vision.apollo.ups.domain.MenuTemplate code="vss_0304" name="录像配置" iconUrl="video-config" authCode="vms_030000" nodeTree=",0,vss_03,vss_0304," url="{'appCode':'100005','menuCode':'vms_03'}" openType="2" display="1" weight="96" appTypeCode="vss" parentCode="vss_03" />
	<vision.apollo.ups.domain.MenuTemplate code="vss_0305" name="备份管理" iconUrl="Backup" url="{'appCode':'100005','menuCode':'vms_04'}" authCode="vms_040000" openType="2" nodeTree=",0,vss_03,vss_0305," display="1" weight="95" appTypeCode="vss" parentCode="vss_03" />
	<vision.apollo.ups.domain.MenuTemplate code="vss_0306" name="业务报警" iconUrl="intelligence-config" authCode="VSS_000205" nodeTree=",0,vss_03,vss_0306," url="/web/smartConfig.action" openType="2" display="1" weight="94" appTypeCode="vss" parentCode="vss_03" />
	<vision.apollo.ups.domain.MenuTemplate code="vss_0307" name="系统参数" iconUrl="config-center" authCode="vms_060000" nodeTree=",0,vss_03,vss_0307," url="{'appCode':'100005','menuCode':'vms_06'}" openType="2" display="1" weight="92" appTypeCode="vss" parentCode="vss_03" />
	<vision.apollo.ups.domain.MenuTemplate code="vss_0308" name="任务计划" iconUrl="task-plan" authCode="vms_050000" openType="2" nodeTree=",0,vss_03,vss_0308," appTypeCode="vss" parentCode="vss_03" url="{'appCode':'100005','menuCode':'vms_05'}" display="1" weight="93" />
	
	<!--视频督察新增KMS数据字典-->
	
	<vision.apollo.publicservice.module.dict.domain.DataDictType code="01020000000" parentCode="0" defaultValue="" caption="严重程度" appCode="vss" creator="admin" createTime="2014-09-28 11:47:41" updateTime="2014-09-28 11:47:41" />
	<vision.apollo.publicservice.module.dict.domain.DataDict typeCode="01020000000" key="vss.01020000000.01020100000" value="01020100000" name="严重" label="label" used="1" creator="admin" remarks="" createTime="2014-09-28 11:48:45" updateTime="2014-09-28 11:48:45" />
	<vision.apollo.publicservice.module.dict.domain.DataDict typeCode="01020000000" key="vss.01020000000.01020200000" value="01020200000" name="一般" label="label" used="1" creator="admin" remarks="" createTime="2014-09-28 11:48:45" updateTime="2014-09-28 11:48:45" />
	<vision.apollo.publicservice.module.dict.domain.DataDict typeCode="01020000000" key="vss.01020000000.01020300000" value="01020300000" name="轻微" label="label" used="1" creator="admin" remarks="" createTime="2014-09-28 11:48:45" updateTime="2014-09-28 11:48:45" />

	<vision.apollo.publicservice.module.dict.domain.DataDictType code="01040000000" parentCode="0" defaultValue="" caption="警种分类" appCode="vss" creator="admin" createTime="2014-09-28 11:47:41" updateTime="2014-09-28 11:47:41" />
	<vision.apollo.publicservice.module.dict.domain.DataDict typeCode="01040000000" key="vss.01040000000.1" value="1" name="国保" label="label" used="1" creator="admin" remarks="" createTime="2014-09-28 11:49:50" updateTime="2014-09-28 11:49:50" />
	<vision.apollo.publicservice.module.dict.domain.DataDict typeCode="01040000000" key="vss.01040000000.2" value="2" name="经侦" label="label" used="1" creator="admin" remarks="" createTime="2014-09-28 11:49:50" updateTime="2014-09-28 11:49:50" />
	<vision.apollo.publicservice.module.dict.domain.DataDict typeCode="01040000000" key="vss.01040000000.3" value="3" name="治安" label="label" used="1" creator="admin" remarks="" createTime="2014-09-28 11:49:50" updateTime="2014-09-28 11:49:50" />
	<vision.apollo.publicservice.module.dict.domain.DataDict typeCode="01040000000" key="vss.01040000000.4" value="4" name="刑侦" label="label" used="1" creator="admin" remarks="" createTime="2014-09-28 11:49:50" updateTime="2014-09-28 11:49:50" />
	<vision.apollo.publicservice.module.dict.domain.DataDict typeCode="01040000000" key="vss.01040000000.5" value="5" name="出入境" label="label" used="1" creator="admin" remarks="" createTime="2014-09-28 11:49:50" updateTime="2014-09-28 11:49:50" />
	<vision.apollo.publicservice.module.dict.domain.DataDict typeCode="01040000000" key="vss.01040000000.6" value="6" name="消防" label="label" used="1" creator="admin" remarks="" createTime="2014-09-28 11:49:50" updateTime="2014-09-28 11:49:50" />
	<vision.apollo.publicservice.module.dict.domain.DataDict typeCode="01040000000" key="vss.01040000000.7" value="7" name="网侦" label="label" used="1" creator="admin" remarks="" createTime="2014-09-28 11:49:50" updateTime="2014-09-28 11:49:50" />
	<vision.apollo.publicservice.module.dict.domain.DataDict typeCode="01040000000" key="vss.01040000000.8" value="8" name="行动技术" label="label" used="1" creator="admin" remarks="" createTime="2014-09-28 11:49:50" updateTime="2014-09-28 11:49:50" />
	<vision.apollo.publicservice.module.dict.domain.DataDict typeCode="01040000000" key="vss.01040000000.9" value="9" name="监管" label="label" used="1" creator="admin" remarks="" createTime="2014-09-28 11:49:50" updateTime="2014-09-28 11:49:50" />
	<vision.apollo.publicservice.module.dict.domain.DataDict typeCode="01040000000" key="vss.01040000000.10" value="10" name="交警" label="label" used="1" creator="admin" remarks="" createTime="2014-09-28 11:49:50" updateTime="2014-09-28 11:49:50" />
	<vision.apollo.publicservice.module.dict.domain.DataDict typeCode="01040000000" key="vss.01040000000.11" value="11" name="法制" label="label" used="1" creator="admin" remarks="" createTime="2014-09-28 11:49:50" updateTime="2014-09-28 11:49:50" />
	<vision.apollo.publicservice.module.dict.domain.DataDict typeCode="01040000000" key="vss.01040000000.12" value="12" name="禁毒" label="label" used="1" creator="admin" remarks="" createTime="2014-09-28 11:49:50" updateTime="2014-09-28 11:49:50" />
	<vision.apollo.publicservice.module.dict.domain.DataDict typeCode="01040000000" key="vss.01040000000.13" value="13" name="反邪教" label="label" used="1" creator="admin" remarks="" createTime="2014-09-28 11:49:50" updateTime="2014-09-28 11:49:50" />
	<vision.apollo.publicservice.module.dict.domain.DataDict typeCode="01040000000" key="vss.01040000000.14" value="14" name="反恐" label="label" used="1" creator="admin" remarks="" createTime="2014-09-28 11:49:50" updateTime="2014-09-28 11:49:50" />


	<vision.apollo.publicservice.module.dict.domain.DataDictType code="010000" parentCode="0" defaultValue="" caption="督察问题分类" appCode="vss" creator="admin" createTime="2014-09-28 11:47:41" updateTime="2014-09-28 11:47:41" />
	<vision.apollo.publicservice.module.dict.domain.DataDict typeCode="010000" key="vss.010000.01010000" value="01010000" name="视频监控设施类" label="视频监控设施类" used="1" creator="admin" remarks="" createTime="2014-09-28 11:50:24" updateTime="2014-09-28 11:50:24" />
	<vision.apollo.publicservice.module.dict.domain.DataDict typeCode="010000" key="vss.010000.01020000" value="01020000" name="执法办案类" label="执法办案类" used="1" creator="admin" remarks="" createTime="2014-09-28 11:50:24" updateTime="2014-09-28 11:50:24" />
	<vision.apollo.publicservice.module.dict.domain.DataDict typeCode="010000" key="vss.010000.01030000" value="01030000" name="窗口服务类" label="窗口服务类" used="1" creator="admin" remarks="" createTime="2014-09-28 11:50:24" updateTime="2014-09-28 11:50:24" />
	<vision.apollo.publicservice.module.dict.domain.DataDict typeCode="010000" key="vss.010000.01040000" value="01040000" name="内部管理类" label="内部管理类" used="1" creator="admin" remarks="" createTime="2014-09-28 11:50:24" updateTime="2014-09-28 11:50:24" />
	<vision.apollo.publicservice.module.dict.domain.DataDict typeCode="010000" key="vss.010000.01990000" value="01990000" name="其他视频督察问题" label="其他视频督察问题" used="1" creator="admin" remarks="" createTime="2014-09-28 11:50:24" updateTime="2014-09-28 11:50:24" />

	<vision.apollo.publicservice.module.dict.domain.DataDictType code="01010000" parentCode="0" defaultValue="" caption="监控设施类" appCode="vss" creator="admin" createTime="2014-09-28 11:47:41" updateTime="2014-09-28 11:47:41" />
	<vision.apollo.publicservice.module.dict.domain.DataDict typeCode="01010000" key="vss.01010000.01010100" value="01010100" name="监控设备故障或无视频信号" label="监控设备故障或无视频信号" used="1" creator="admin" remarks="" createTime="2014-09-28 11:51:07" updateTime="2014-09-28 11:51:07" />
	<vision.apollo.publicservice.module.dict.domain.DataDict typeCode="01010000" key="vss.01010000.01010200" value="01010200" name="偏移、污损、遮挡监控探头" label="偏移、污损、遮挡监控探头" used="1" creator="admin" remarks="" createTime="2014-09-28 11:51:07" updateTime="2014-09-28 11:51:07" />
	<vision.apollo.publicservice.module.dict.domain.DataDict typeCode="01010000" key="vss.01010000.01010300" value="01010300" name="前端设置不规范" label="前端设置不规范" used="1" creator="admin" remarks="" createTime="2014-09-28 11:51:07" updateTime="2014-09-28 11:51:07" />
	<vision.apollo.publicservice.module.dict.domain.DataDict typeCode="01010000" key="vss.01010000.01010400" value="01010400" name="未按要求存储或故意删除、隐匿监控资料" label="未按要求存储或故意删除、隐匿监控资料" used="1" creator="admin" remarks="" createTime="2014-09-28 11:51:07" updateTime="2014-09-28 11:51:07" />
	<vision.apollo.publicservice.module.dict.domain.DataDict typeCode="01010000" key="vss.01010000.01019900" value="01019900" name="其他监控设施问题" label="其他监控设施问题" used="1" creator="admin" remarks="" createTime="2014-09-28 11:51:07" updateTime="2014-09-28 11:51:07" />

	<vision.apollo.publicservice.module.dict.domain.DataDictType code="01020000" parentCode="0" defaultValue="" caption="执法办案类" appCode="vss" creator="admin" createTime="2014-09-28 11:47:41" updateTime="2014-09-28 11:47:41" />
	<vision.apollo.publicservice.module.dict.domain.DataDict typeCode="01020000" key="vss.01020000.01020100" value="01020100" name="违法犯罪嫌疑人被带至公安机关后，未直接带入办案区" label="违法犯罪嫌疑人被带至公安机关后，未直接带入办案区" used="1" creator="admin" remarks="" createTime="2014-09-28 11:51:24" updateTime="2014-09-28 11:51:24" />
	<vision.apollo.publicservice.module.dict.domain.DataDict typeCode="01020000" key="vss.01020000.01020200" value="01020200" name="违法犯罪嫌疑人进入办案区后，未先进行人身检查和信息采集" label="违法犯罪嫌疑人进入办案区后，未先进行人身检查和信息采集" used="1" creator="admin" remarks="" createTime="2014-09-28 11:51:24" updateTime="2014-09-28 11:51:24" />
	<vision.apollo.publicservice.module.dict.domain.DataDict typeCode="01020000" key="vss.01020000.01020300" value="01020300" name="违法犯罪嫌疑人在办案区内，无人看管或看管不力" label="违法犯罪嫌疑人在办案区内，无人看管或看管不力" used="1" creator="admin" remarks="" createTime="2014-09-28 11:51:24" updateTime="2014-09-28 11:51:24" />
	<vision.apollo.publicservice.module.dict.domain.DataDict typeCode="01020000" key="vss.01020000.01020400" value="01020400" name="未在办案区对违法犯罪嫌疑人进行讯（询）问" label="未在办案区对违法犯罪嫌疑人进行讯（询）问" used="1" creator="admin" remarks="" createTime="2014-09-28 11:51:24" updateTime="2014-09-28 11:51:24" />
	<vision.apollo.publicservice.module.dict.domain.DataDict typeCode="01020000" key="vss.01020000.01020500" value="01020500" name="办案区存在安全隐患或使用不规范" label="办案区存在安全隐患或使用不规范" used="1" creator="admin" remarks="" createTime="2014-09-28 11:51:24" updateTime="2014-09-28 11:51:24" />
	<vision.apollo.publicservice.module.dict.domain.DataDict typeCode="01020000" key="vss.01020000.01020600" value="01020600" name="民警单人讯（询）问或非正式民警进行讯（询）问" label="民警单人讯（询）问或非正式民警进行讯（询）问" used="1" creator="admin" remarks="" createTime="2014-09-28 11:51:24" updateTime="2014-09-28 11:51:24" />
	<vision.apollo.publicservice.module.dict.domain.DataDict typeCode="01020000" key="vss.01020000.01020700" value="01020700" name="询问、讯问、继续盘问超过法定时限" label="询问、讯问、继续盘问超过法定时限" used="1" creator="admin" remarks="" createTime="2014-09-28 11:51:24" updateTime="2014-09-28 11:51:24" />
	<vision.apollo.publicservice.module.dict.domain.DataDict typeCode="01020000" key="vss.01020000.01020800" value="01020800" name="未按规定使用械具" label="未按规定使用械具" used="1" creator="admin" remarks="" createTime="2014-09-28 11:51:24" updateTime="2014-09-28 11:51:24" />
	<vision.apollo.publicservice.module.dict.domain.DataDict typeCode="01020000" key="vss.01020000.01020900" value="01020900" name="未及时发现、制止违法犯罪嫌疑人或在押人员自伤、自残、自杀、逃脱" label="未及时发现、制止违法犯罪嫌疑人或在押人员自伤、自残、自杀、逃脱" used="1" creator="admin" remarks="" createTime="2014-09-28 11:51:24" updateTime="2014-09-28 11:51:24" />
	<vision.apollo.publicservice.module.dict.domain.DataDict typeCode="01020000" key="vss.01020000.01021000" value="01021000" name="打骂体罚虐待违法犯罪嫌疑人或在押人员" label="打骂体罚虐待违法犯罪嫌疑人或在押人员" used="1" creator="admin" remarks="" createTime="2014-09-28 11:51:24" updateTime="2014-09-28 11:51:24" />
	<vision.apollo.publicservice.module.dict.domain.DataDict typeCode="01020000" key="vss.01020000.01021100" value="01021100" name="监区内违规携带或使用通讯工具" label="监区内违规携带或使用通讯工具" used="1" creator="admin" remarks="" createTime="2014-09-28 11:51:24" updateTime="2014-09-28 11:51:24" />
	<vision.apollo.publicservice.module.dict.domain.DataDict typeCode="01020000" key="vss.01020000.01021200" value="01021200" name="监室存在安全隐患" label="监室存在安全隐患" used="1" creator="admin" remarks="" createTime="2014-09-28 11:51:24" updateTime="2014-09-28 11:51:24" />
	<vision.apollo.publicservice.module.dict.domain.DataDict typeCode="01020000" key="vss.01020000.01021300" value="01021300" name="监所监控岗位民警不在岗或不尽责" label="监所监控岗位民警不在岗或不尽责" used="1" creator="admin" remarks="" createTime="2014-09-28 11:51:24" updateTime="2014-09-28 11:51:24" />
	<vision.apollo.publicservice.module.dict.domain.DataDict typeCode="01020000" key="vss.01020000.01021400" value="01021400" name="监所未按规定开展巡视" label="监所未按规定开展巡视" used="1" creator="admin" remarks="" createTime="2014-09-28 11:51:24" updateTime="2014-09-28 11:51:24" />
	<vision.apollo.publicservice.module.dict.domain.DataDict typeCode="01020000" key="vss.01020000.01029900" value="01029900" name="其他执法办案问题" label="其他执法办案问题" used="1" creator="admin" remarks="" createTime="2014-09-28 11:51:24" updateTime="2014-09-28 11:51:24" />


	<vision.apollo.publicservice.module.dict.domain.DataDictType code="01030000" parentCode="0" defaultValue="" caption="窗口服务类" appCode="vss" creator="admin" createTime="2014-09-28 11:47:41" updateTime="2014-09-28 11:47:41" />
	<vision.apollo.publicservice.module.dict.domain.DataDict typeCode="01030000" key="vss.01030000.01030100" value="01030100" name="便民设施不全" label="便民设施不全" used="1" creator="admin" remarks="" createTime="2014-09-28 11:51:49" updateTime="2014-09-28 11:51:49" />
	<vision.apollo.publicservice.module.dict.domain.DataDict typeCode="01030000" key="vss.01030000.01030200" value="01030200" name="民警或工作人员不在岗" label="民警或工作人员不在岗" used="1" creator="admin" remarks="" createTime="2014-09-28 11:51:49" updateTime="2014-09-28 11:51:49" />
	<vision.apollo.publicservice.module.dict.domain.DataDict typeCode="01030000" key="vss.01030000.01030300" value="01030300" name="服务态度差" label="服务态度差" used="1" creator="admin" remarks="" createTime="2014-09-28 11:51:49" updateTime="2014-09-28 11:51:49" />
	<vision.apollo.publicservice.module.dict.domain.DataDict typeCode="01030000" key="vss.01030000.01030400" value="01030400" name="行为举止不当" label="行为举止不当" used="1" creator="admin" remarks="" createTime="2014-09-28 11:51:49" updateTime="2014-09-28 11:51:49" />
	<vision.apollo.publicservice.module.dict.domain.DataDict typeCode="01030000" key="vss.01030000.01030500" value="01030500" name="警容风纪不整" label="警容风纪不整" used="1" creator="admin" remarks="" createTime="2014-09-28 11:51:49" updateTime="2014-09-28 11:51:49" />
	<vision.apollo.publicservice.module.dict.domain.DataDict typeCode="01030000" key="vss.01030000.01030600" value="01030600" name="内务卫生差" label="内务卫生差" used="1" creator="admin" remarks="" createTime="2014-09-28 11:51:49" updateTime="2014-09-28 11:51:49" />
	<vision.apollo.publicservice.module.dict.domain.DataDict typeCode="01030000" key="vss.01030000.01039900" value="01039900" name="其他窗口服务问题" label="其他窗口服务问题" used="1" creator="admin" remarks="" createTime="2014-09-28 11:51:49" updateTime="2014-09-28 11:51:49" />

	<vision.apollo.publicservice.module.dict.domain.DataDictType code="01040000" parentCode="0" defaultValue="" caption="内部管理类" appCode="vss" creator="admin" createTime="2014-09-28 11:47:41" updateTime="2014-09-28 11:47:41" />
	<vision.apollo.publicservice.module.dict.domain.DataDict typeCode="01040000" key="vss.01040000.01040100" value="01040100" name="枪支管理不规范" label="枪支管理不规范" used="1" creator="admin" remarks="" createTime="2014-09-28 11:52:11" updateTime="2014-09-28 11:52:11" />
	<vision.apollo.publicservice.module.dict.domain.DataDict typeCode="01040000" key="vss.01040000.01040200" value="01040200" name="内部安全防范不到位" label="内部安全防范不到位" used="1" creator="admin" remarks="" createTime="2014-09-28 11:52:11" updateTime="2014-09-28 11:52:11" />
	<vision.apollo.publicservice.module.dict.domain.DataDict typeCode="01040000" key="vss.01040000.01049900" value="01049900" name="其他内部管理问题" label="其他内部管理问题" used="1" creator="admin" remarks="" createTime="2014-09-28 11:52:11" updateTime="2014-09-28 11:52:11" />

	<vision.apollo.publicservice.module.dict.domain.DataDictType code="02020000000" parentCode="0" defaultValue="" caption="是否重点监控区域" appCode="vss" creator="admin" createTime="2014-09-28 11:47:41" updateTime="2014-09-28 11:47:41" />
	<vision.apollo.publicservice.module.dict.domain.DataDict typeCode="02020000000" key="vss.02020000000.02020100000" value="02020100000" name="否" label="label" used="1" creator="admin" remarks="" createTime="2014-09-28 11:52:27" updateTime="2014-09-28 11:52:27" />
	<vision.apollo.publicservice.module.dict.domain.DataDict typeCode="02020000000" key="vss.02020000000.02020200000" value="02020200000" name="是" label="label" used="1" creator="admin" remarks="" createTime="2014-09-28 11:52:27" updateTime="2014-09-28 11:52:27" />

	<vision.apollo.publicservice.module.dict.domain.DataDictType code="0000" parentCode="0" defaultValue="" caption="监控区域类型" appCode="vss" creator="admin" createTime="2014-09-28 11:47:41" updateTime="2014-09-28 11:47:41" />
	<vision.apollo.publicservice.module.dict.domain.DataDict typeCode="0000" key="vss.0000.0100" value="0100" name="办案场所" label="办案场所" used="1" creator="admin" remarks="" createTime="2014-09-28 11:50:24" updateTime="2014-09-28 11:50:24" />
	<vision.apollo.publicservice.module.dict.domain.DataDict typeCode="0000" key="vss.0000.0200" value="0200" name="服务场所" label="服务场所" used="1" creator="admin" remarks="" createTime="2014-09-28 11:50:24" updateTime="2014-09-28 11:50:24" />
	<vision.apollo.publicservice.module.dict.domain.DataDict typeCode="0000" key="vss.0000.0300" value="0300" name="办公场所" label="办公场所" used="1" creator="admin" remarks="" createTime="2014-09-28 11:50:24" updateTime="2014-09-28 11:50:24" />
	<vision.apollo.publicservice.module.dict.domain.DataDict typeCode="0000" key="vss.0000.0400" value="0400" name="监管场所" label="监管场所" used="1" creator="admin" remarks="" createTime="2014-09-28 11:50:24" updateTime="2014-09-28 11:50:24" />
	<vision.apollo.publicservice.module.dict.domain.DataDict typeCode="0000" key="vss.0000.0500" value="0500" name="武器保管场所" label="武器保管场所" used="1" creator="admin" remarks="" createTime="2014-09-28 11:50:24" updateTime="2014-09-28 11:50:24" />
	<vision.apollo.publicservice.module.dict.domain.DataDict typeCode="0000" key="vss.0000.0600" value="0600" name="治安检查场所" label="治安检查场所" used="1" creator="admin" remarks="" createTime="2014-09-28 11:50:24" updateTime="2014-09-28 11:50:24" />
	<vision.apollo.publicservice.module.dict.domain.DataDict typeCode="0000" key="vss.0000.9900" value="9900" name="其他" label="其他" used="1" creator="admin" remarks="" createTime="2014-09-28 11:50:24" updateTime="2014-09-28 11:50:24" />

	<vision.apollo.publicservice.module.dict.domain.DataDictType code="0100" parentCode="0" defaultValue="" caption="办案场所" appCode="vss" creator="admin" createTime="2014-09-28 11:47:41" updateTime="2014-09-28 11:47:41" />
	<vision.apollo.publicservice.module.dict.domain.DataDict typeCode="0100" key="vss.0100.0101" value="0101" name="询问室" label="询问室" used="1" creator="admin" remarks="" createTime="2014-09-28 11:51:07" updateTime="2014-09-28 11:51:07" />
	<vision.apollo.publicservice.module.dict.domain.DataDict typeCode="0100" key="vss.0100.0102" value="0102" name="讯问室" label="讯问室" used="1" creator="admin" remarks="" createTime="2014-09-28 11:51:07" updateTime="2014-09-28 11:51:07" />
	<vision.apollo.publicservice.module.dict.domain.DataDict typeCode="0100" key="vss.0100.0103" value="0103" name="侯问室" label="侯问室" used="1" creator="admin" remarks="" createTime="2014-09-28 11:51:07" updateTime="2014-09-28 11:51:07" />
	<vision.apollo.publicservice.module.dict.domain.DataDict typeCode="0100" key="vss.0100.0104" value="0104" name="约束室" label="约束室" used="1" creator="admin" remarks="" createTime="2014-09-28 11:51:07" updateTime="2014-09-28 11:51:07" />
	<vision.apollo.publicservice.module.dict.domain.DataDict typeCode="0100" key="vss.0100.0105" value="0105" name="醒酒室" label="醒酒室" used="1" creator="admin" remarks="" createTime="2014-09-28 11:51:07" updateTime="2014-09-28 11:51:07" />
	<vision.apollo.publicservice.module.dict.domain.DataDict typeCode="0100" key="vss.0100.0106" value="0106" name="辨认室" label="辨认室" used="1" creator="admin" remarks="" createTime="2014-09-28 11:51:07" updateTime="2014-09-28 11:51:07" />
	<vision.apollo.publicservice.module.dict.domain.DataDict typeCode="0100" key="vss.0100.0107" value="0107" name="人身安全检查室" label="人身安全检查室" used="1" creator="admin" remarks="" createTime="2014-09-28 11:51:07" updateTime="2014-09-28 11:51:07" />
	<vision.apollo.publicservice.module.dict.domain.DataDict typeCode="0100" key="vss.0100.0108" value="0108" name="物证保管室" label="物证保管室" used="1" creator="admin" remarks="" createTime="2014-09-28 11:51:07" updateTime="2014-09-28 11:51:07" />
	<vision.apollo.publicservice.module.dict.domain.DataDict typeCode="0100" key="vss.0100.0109" value="0109" name="信息采集室" label="信息采集室" used="1" creator="admin" remarks="" createTime="2014-09-28 11:51:07" updateTime="2014-09-28 11:51:07" />
	<vision.apollo.publicservice.module.dict.domain.DataDict typeCode="0100" key="vss.0100.0110" value="0110" name="纠纷调处室" label="纠纷调处室" used="1" creator="admin" remarks="" createTime="2014-09-28 11:51:07" updateTime="2014-09-28 11:51:07" />
	<vision.apollo.publicservice.module.dict.domain.DataDict typeCode="0100" key="vss.0100.0199" value="0199" name="其他" label="其他" used="1" creator="admin" remarks="" createTime="2014-09-28 11:51:07" updateTime="2014-09-28 11:51:07" />

	<vision.apollo.publicservice.module.dict.domain.DataDictType code="0200" parentCode="0" defaultValue="" caption="服务场所" appCode="vss" creator="admin" createTime="2014-09-28 11:47:41" updateTime="2014-09-28 11:47:41" />
	<vision.apollo.publicservice.module.dict.domain.DataDict typeCode="0200" key="vss.0200.0201" value="0201" name="户籍室" label="户籍室" used="1" creator="admin" remarks="" createTime="2014-09-28 11:51:07" updateTime="2014-09-28 11:51:07" />
	<vision.apollo.publicservice.module.dict.domain.DataDict typeCode="0200" key="vss.0200.0202" value="0202" name="接待室" label="接待室" used="1" creator="admin" remarks="" createTime="2014-09-28 11:51:07" updateTime="2014-09-28 11:51:07" />
	<vision.apollo.publicservice.module.dict.domain.DataDict typeCode="0200" key="vss.0200.0203" value="0203" name="等候室" label="等候室" used="1" creator="admin" remarks="" createTime="2014-09-28 11:51:07" updateTime="2014-09-28 11:51:07" />
	<vision.apollo.publicservice.module.dict.domain.DataDict typeCode="0200" key="vss.0200.0204" value="0204" name="信访接待室" label="信访接待室" used="1" creator="admin" remarks="" createTime="2014-09-28 11:51:07" updateTime="2014-09-28 11:51:07" />
	<vision.apollo.publicservice.module.dict.domain.DataDict typeCode="0200" key="vss.0200.0205" value="0205" name="出入境服务大厅" label="出入境服务大厅" used="1" creator="admin" remarks="" createTime="2014-09-28 11:51:07" updateTime="2014-09-28 11:51:07" />
	<vision.apollo.publicservice.module.dict.domain.DataDict typeCode="0200" key="vss.0200.0206" value="0206" name="车、驾管服务大厅" label="车、驾管服务大厅" used="1" creator="admin" remarks="" createTime="2014-09-28 11:51:07" updateTime="2014-09-28 11:51:07" />
	<vision.apollo.publicservice.module.dict.domain.DataDict typeCode="0200" key="vss.0200.0207" value="0207" name="消防服务大厅" label="消防服务大厅" used="1" creator="admin" remarks="" createTime="2014-09-28 11:51:07" updateTime="2014-09-28 11:51:07" />
	<vision.apollo.publicservice.module.dict.domain.DataDict typeCode="0200" key="vss.0200.0208" value="0208" name="事故处理大厅" label="事故处理大厅" used="1" creator="admin" remarks="" createTime="2014-09-28 11:51:07" updateTime="2014-09-28 11:51:07" />
	<vision.apollo.publicservice.module.dict.domain.DataDict typeCode="0200" key="vss.0200.0209" value="0209" name="综合服务大厅" label="综合服务大厅" used="1" creator="admin" remarks="" createTime="2014-09-28 11:51:07" updateTime="2014-09-28 11:51:07" />
	<vision.apollo.publicservice.module.dict.domain.DataDict typeCode="0200" key="vss.0200.0210" value="0210" name="驾驶员科目考试室" label="驾驶员科目考试室" used="1" creator="admin" remarks="" createTime="2014-09-28 11:51:07" updateTime="2014-09-28 11:51:07" />
	<vision.apollo.publicservice.module.dict.domain.DataDict typeCode="0200" key="vss.0200.0211" value="0211" name="交通违法处理室" label="交通违法处理室" used="1" creator="admin" remarks="" createTime="2014-09-28 11:51:07" updateTime="2014-09-28 11:51:07" />
	<vision.apollo.publicservice.module.dict.domain.DataDict typeCode="0200" key="vss.0200.0212" value="0212" name="出入境口岸服务大厅" label="出入境口岸服务大厅" used="1" creator="admin" remarks="" createTime="2014-09-28 11:51:07" updateTime="2014-09-28 11:51:07" />
	<vision.apollo.publicservice.module.dict.domain.DataDict typeCode="0200" key="vss.0200.0299" value="0299" name="其他" label="其他" used="1" creator="admin" remarks="" createTime="2014-09-28 11:51:07" updateTime="2014-09-28 11:51:07" />

	<vision.apollo.publicservice.module.dict.domain.DataDictType code="0300" parentCode="0" defaultValue="" caption="办公场所" appCode="vss" creator="admin" createTime="2014-09-28 11:47:41" updateTime="2014-09-28 11:47:41" />
	<vision.apollo.publicservice.module.dict.domain.DataDict typeCode="0300" key="vss.0300.0301" value="0301" name="备勤室" label="备勤室" used="1" creator="admin" remarks="" createTime="2014-09-28 11:51:07" updateTime="2014-09-28 11:51:07" />
	<vision.apollo.publicservice.module.dict.domain.DataDict typeCode="0300" key="vss.0300.0302" value="0302" name="接处警厅（室）" label="接处警厅（室）" used="1" creator="admin" remarks="" createTime="2014-09-28 11:51:07" updateTime="2014-09-28 11:51:07" />
	<vision.apollo.publicservice.module.dict.domain.DataDict typeCode="0300" key="vss.0300.0303" value="0303" name="现场勘验室" label="现场勘验室" used="1" creator="admin" remarks="" createTime="2014-09-28 11:51:07" updateTime="2014-09-28 11:51:07" />
	<vision.apollo.publicservice.module.dict.domain.DataDict typeCode="0300" key="vss.0300.0304" value="0304" name="指挥调度大厅（室）" label="指挥调度大厅（室）" used="1" creator="admin" remarks="" createTime="2014-09-28 11:51:07" updateTime="2014-09-28 11:51:07" />
	<vision.apollo.publicservice.module.dict.domain.DataDict typeCode="0300" key="vss.0300.0305" value="0305" name="值班室" label="值班室" used="1" creator="admin" remarks="" createTime="2014-09-28 11:51:07" updateTime="2014-09-28 11:51:07" />
	<vision.apollo.publicservice.module.dict.domain.DataDict typeCode="0300" key="vss.0300.0306" value="0306" name="会议室" label="会议室" used="1" creator="admin" remarks="" createTime="2014-09-28 11:51:07" updateTime="2014-09-28 11:51:07" />
	<vision.apollo.publicservice.module.dict.domain.DataDict typeCode="0300" key="vss.0300.0307" value="0307" name="出入口" label="出入口" used="1" creator="admin" remarks="" createTime="2014-09-28 11:51:07" updateTime="2014-09-28 11:51:07" />
	<vision.apollo.publicservice.module.dict.domain.DataDict typeCode="0300" key="vss.0300.0308" value="0308" name="院内" label="院内" used="1" creator="admin" remarks="" createTime="2014-09-28 11:51:07" updateTime="2014-09-28 11:51:07" />
	<vision.apollo.publicservice.module.dict.domain.DataDict typeCode="0300" key="vss.0300.0309" value="0309" name="走廊" label="走廊" used="1" creator="admin" remarks="" createTime="2014-09-28 11:51:07" updateTime="2014-09-28 11:51:07" />
	<vision.apollo.publicservice.module.dict.domain.DataDict typeCode="0300" key="vss.0300.0310" value="0310" name="哨位" label="哨位" used="1" creator="admin" remarks="" createTime="2014-09-28 11:51:07" updateTime="2014-09-28 11:51:07" />
	<vision.apollo.publicservice.module.dict.domain.DataDict typeCode="0300" key="vss.0300.0399" value="0399" name="其他" label="其他" used="1" creator="admin" remarks="" createTime="2014-09-28 11:51:07" updateTime="2014-09-28 11:51:07" />

	<vision.apollo.publicservice.module.dict.domain.DataDictType code="0400" parentCode="0" defaultValue="" caption="监管场所" appCode="vss" creator="admin" createTime="2014-09-28 11:47:41" updateTime="2014-09-28 11:47:41" />
	<vision.apollo.publicservice.module.dict.domain.DataDict typeCode="0400" key="vss.0400.0401" value="0401" name="拘留所询问室" label="拘留所询问室" used="1" creator="admin" remarks="" createTime="2014-09-28 11:51:07" updateTime="2014-09-28 11:51:07" />
	<vision.apollo.publicservice.module.dict.domain.DataDict typeCode="0400" key="vss.0400.0402" value="0402" name="看守所讯问室" label="看守所讯问室" used="1" creator="admin" remarks="" createTime="2014-09-28 11:51:07" updateTime="2014-09-28 11:51:07" />
	<vision.apollo.publicservice.module.dict.domain.DataDict typeCode="0400" key="vss.0400.0403" value="0403" name="监控室" label="监控室" used="1" creator="admin" remarks="" createTime="2014-09-28 11:51:07" updateTime="2014-09-28 11:51:07" />
	<vision.apollo.publicservice.module.dict.domain.DataDict typeCode="0400" key="vss.0400.0404" value="0404" name="双门互锁区" label="双门互锁区" used="1" creator="admin" remarks="" createTime="2014-09-28 11:51:07" updateTime="2014-09-28 11:51:07" />
	<vision.apollo.publicservice.module.dict.domain.DataDict typeCode="0400" key="vss.0400.0405" value="0405" name="内值班室" label="内值班室" used="1" creator="admin" remarks="" createTime="2014-09-28 11:51:07" updateTime="2014-09-28 11:51:07" />
	<vision.apollo.publicservice.module.dict.domain.DataDict typeCode="0400" key="vss.0400.0406" value="0406" name="巡视走廊" label="巡视走廊" used="1" creator="admin" remarks="" createTime="2014-09-28 11:51:07" updateTime="2014-09-28 11:51:07" />
	<vision.apollo.publicservice.module.dict.domain.DataDict typeCode="0400" key="vss.0400.0407" value="0407" name="收押大厅" label="收押大厅" used="1" creator="admin" remarks="" createTime="2014-09-28 11:51:07" updateTime="2014-09-28 11:51:07" />
	<vision.apollo.publicservice.module.dict.domain.DataDict typeCode="0400" key="vss.0400.0408" value="0408" name="收拘大厅" label="收拘大厅" used="1" creator="admin" remarks="" createTime="2014-09-28 11:51:07" updateTime="2014-09-28 11:51:07" />
	<vision.apollo.publicservice.module.dict.domain.DataDict typeCode="0400" key="vss.0400.0409" value="0409" name="律师会见室" label="律师会见室" used="1" creator="admin" remarks="" createTime="2014-09-28 11:51:07" updateTime="2014-09-28 11:51:07" />
	<vision.apollo.publicservice.module.dict.domain.DataDict typeCode="0400" key="vss.0400.0499" value="0499" name="其他" label="其他" used="1" creator="admin" remarks="" createTime="2014-09-28 11:51:07" updateTime="2014-09-28 11:51:07" />

	<vision.apollo.publicservice.module.dict.domain.DataDictType code="0500" parentCode="0" defaultValue="" caption="武器保管场所" appCode="vss" creator="admin" createTime="2014-09-28 11:47:41" updateTime="2014-09-28 11:47:41" />
	<vision.apollo.publicservice.module.dict.domain.DataDict typeCode="0500" key="vss.0500.0501" value="0501" name="枪库" label="枪库" used="1" creator="admin" remarks="" createTime="2014-09-28 11:51:07" updateTime="2014-09-28 11:51:07" />
	<vision.apollo.publicservice.module.dict.domain.DataDict typeCode="0500" key="vss.0500.0502" value="0502" name="弹库" label="弹库" used="1" creator="admin" remarks="" createTime="2014-09-28 11:51:07" updateTime="2014-09-28 11:51:07" />
	<vision.apollo.publicservice.module.dict.domain.DataDict typeCode="0500" key="vss.0500.0503" value="0503" name="警械装备室" label="警械装备室" used="1" creator="admin" remarks="" createTime="2014-09-28 11:51:07" updateTime="2014-09-28 11:51:07" />
	<vision.apollo.publicservice.module.dict.domain.DataDict typeCode="0500" key="vss.0500.0599" value="0599" name="其他" label="其他" used="1" creator="admin" remarks="" createTime="2014-09-28 11:51:07" updateTime="2014-09-28 11:51:07" />

	<vision.apollo.publicservice.module.dict.domain.DataDictType code="0600" parentCode="0" defaultValue="" caption="治安检查场所" appCode="vss" creator="admin" createTime="2014-09-28 11:47:41" updateTime="2014-09-28 11:47:41" />
	<vision.apollo.publicservice.module.dict.domain.DataDict typeCode="0600" key="vss.0600.0601" value="0601" name="治安检查站" label="治安检查站" used="1" creator="admin" remarks="" createTime="2014-09-28 11:51:07" updateTime="2014-09-28 11:51:07" />
	<vision.apollo.publicservice.module.dict.domain.DataDict typeCode="0600" key="vss.0600.0602" value="0602" name="治安卡口" label="治安卡口" used="1" creator="admin" remarks="" createTime="2014-09-28 11:51:07" updateTime="2014-09-28 11:51:07" />
	<vision.apollo.publicservice.module.dict.domain.DataDict typeCode="0600" key="vss.0600.0699" value="0699" name="其他" label="其他" used="1" creator="admin" remarks="" createTime="2014-09-28 11:51:07" updateTime="2014-09-28 11:51:07" />
	
	<vision.apollo.publicservice.module.dict.domain.DataDictType code="01010000000" parentCode="0" defaultValue="" caption="督察类型" appCode="vss" creator="admin" createTime="2014-09-28 11:47:41" updateTime="2014-09-28 11:47:41" />
	<vision.apollo.publicservice.module.dict.domain.DataDict typeCode="01010000000" key="vss.01010000000.0704" value="01010100000" name="日常督察" label="label" used="1" creator="admin" remarks="" createTime="2014-09-28 11:51:07" updateTime="2014-09-28 11:51:07" />
	<vision.apollo.publicservice.module.dict.domain.DataDict typeCode="01010000000" key="vss.01010000000.0705" value="01010200000" name="专项督察" label="label" used="1" creator="admin" remarks="" createTime="2014-09-28 11:51:07" updateTime="2014-09-28 11:51:07" />
	
	<!--公安机关单位-->
	<vision.apollo.publicservice.module.dict.domain.DataDictType code="100000000000" parentCode="0" defaultValue="" caption="涉及单位" appCode="vss" creator="admin" createTime="2016-01-11 11:47:41" updateTime="2016-01-11 11:47:41" />
	
	<vision.apollo.app.domain.AppFieldExt appType="vss"  type="0" fieldName="dubbo" fieldType="text"  dictType="" fieldDisplayName="dubbo端口"  remark="" ></vision.apollo.app.domain.AppFieldExt>
	<vision.apollo.app.domain.AppExt appType="vss"  appCode="200010" domainCode="100001"  extFieldName="dubbo"  extFieldValue="20883" ></vision.apollo.app.domain.AppExt>
	
	<!--V1.6版本新增-->
	<vision.apollo.publicservice.module.dict.domain.DataDictType code="gadcflws" parentCode="0" defaultValue="" caption="公安督察法律文书" appCode="vss" creator="admin" createTime="2014-09-28 11:47:41" updateTime="2014-09-28 11:47:41" />
	<vision.apollo.publicservice.module.dict.domain.DataDict typeCode="gadcflws" key="vss.gadcflws.1" value="1" name="公安督察通知书" label="公安督察通知书" used="1" creator="admin" remarks="" createTime="2016-06-29 11:51:07" updateTime="2016-06-29 11:51:07" />
	<vision.apollo.publicservice.module.dict.domain.DataDict typeCode="gadcflws" key="vss.gadcflws.2" value="2" name="公安督察通知书" label="公安督察通知书" used="1" creator="admin" remarks="" createTime="2016-06-29 11:51:07" updateTime="2016-06-29 11:51:07" />
	<vision.apollo.publicservice.module.dict.domain.DataDict typeCode="gadcflws" key="vss.gadcflws.3" value="3" name="公安督察建议书" label="公安督察建议书" used="1" creator="admin" remarks="" createTime="2016-06-29 11:51:07" updateTime="2016-06-29 11:51:07" />
	<vision.apollo.publicservice.module.dict.domain.DataDict typeCode="gadcflws" key="vss.gadcflws.4" value="4" name="其他公安督察法律文书" label="其他公安督察法律文书" used="1" creator="admin" remarks="" createTime="2016-06-29 11:51:07" updateTime="2016-06-29 11:51:07" />

	<vision.apollo.publicservice.module.dict.domain.DataDictType code="jwdcyscllx" parentCode="0" defaultValue="" caption="警务督察移送处理措施" appCode="vss" creator="admin" createTime="2014-09-28 11:47:41" updateTime="2014-09-28 11:47:41" />
	<vision.apollo.publicservice.module.dict.domain.DataDict typeCode="jwdcyscllx" key="vss.jwdcyscllx.1" value="1" name="移送纪检监察部门建议给予处分" label="移送纪检监察部门建议给予处分" used="1" creator="admin" remarks="" createTime="2016-06-29 11:51:07" updateTime="2016-06-29 11:51:07" />
	<vision.apollo.publicservice.module.dict.domain.DataDict typeCode="jwdcyscllx" key="vss.jwdcyscllx.2" value="2" name="移送司法机关依法处理" label="移送司法机关依法处理" used="1" creator="admin" remarks="" createTime="2016-06-29 11:51:07" updateTime="2016-06-29 11:51:07" />
	<vision.apollo.publicservice.module.dict.domain.DataDict typeCode="jwdcyscllx" key="vss.jwdcyscllx.3" value="3" name="移送其他有关部门依法处理" label="移送其他有关部门依法处理" used="1" creator="admin" remarks="" createTime="2016-06-29 11:51:07" updateTime="2016-06-29 11:51:07" />

	<vision.apollo.publicservice.module.dict.domain.DataDictType code="jwdcxzcs" parentCode="0" defaultValue="" caption="警务督察行政措施" appCode="vss" creator="admin" createTime="2014-09-28 11:47:41" updateTime="2014-09-28 11:47:41" />
	<vision.apollo.publicservice.module.dict.domain.DataDict typeCode="jwdcxzcs" key="vss.jwdcxzcs.1" value="1" name="停止执行职务" label="停止执行职务" used="1" creator="admin" remarks="" createTime="2016-06-29 11:51:07" updateTime="2016-06-29 11:51:07" />
	<vision.apollo.publicservice.module.dict.domain.DataDict typeCode="jwdcxzcs" key="vss.jwdcxzcs.2" value="2" name="禁闭" label="禁闭" used="1" creator="admin" remarks="" createTime="2016-06-29 11:51:07" updateTime="2016-06-29 11:51:07" />

	<vision.apollo.publicservice.module.dict.domain.DataDictType code="jwdcdcczcs" parentCode="0" defaultValue="" caption="警务督察处置措施" appCode="vss" creator="admin" createTime="2014-09-28 11:47:41" updateTime="2014-09-28 11:47:41" />
	<vision.apollo.publicservice.module.dict.domain.DataDict typeCode="jwdcdcczcs" key="vss.jwdcdcczcs.1" value="1" name="当场予以纠正" label="当场予以纠正" used="1" creator="admin" remarks="" createTime="2016-06-29 11:51:07" updateTime="2016-06-29 11:51:07" />
	<vision.apollo.publicservice.module.dict.domain.DataDict typeCode="jwdcdcczcs" key="vss.jwdcdcczcs.2" value="2" name="当场予以扣留" label="当场予以扣留" used="1" creator="admin" remarks="" createTime="2016-06-29 11:51:07" updateTime="2016-06-29 11:51:07" />
	<vision.apollo.publicservice.module.dict.domain.DataDict typeCode="jwdcdcczcs" key="vss.jwdcdcczcs.3" value="3" name="带离现场" label="带离现场" used="1" creator="admin" remarks="" createTime="2016-06-29 11:51:07" updateTime="2016-06-29 11:51:07" />
	
</dbConfig>
